statistics_operation/__init__.py
statistics_operation/main.py
statistics_operation/operations.py
statistics_operation-0.1.0.dist-info/METADATA
statistics_operation-0.1.0.dist-info/WHEEL
statistics_operation-0.1.0.dist-info/RECORD
