Metadata-Version: 2.1
Name: statistics-operation
Version: 0.1.0
Summary: 
Author: sanjeev-manian
Author-email: sanjeev.manian@solitontech.com
Requires-Python: >=3.11,<3.13
Classifier: Programming Language :: Python :: 3
Classifier: Programming Language :: Python :: 3.11
Requires-Dist: numpy (>=1.26.0,<2.0.0)
Requires-Dist: statistics (>=1.0.3.5,<2.0.0.0)
